LICENSE
README.md
setup.cfg
setup.py
ebesumusic.egg-info/PKG-INFO
ebesumusic.egg-info/SOURCES.txt
ebesumusic.egg-info/dependency_links.txt
ebesumusic.egg-info/requires.txt
ebesumusic.egg-info/top_level.txt
kinomusic/__init__.py
kinomusic/_classes.py
kinomusic/_emojis.py
kinomusic/_version.py
kinomusic/checks.py
kinomusic/errors.py
kinomusic/events.py
kinomusic/music.py
kinomusic/paginator.py
kinomusic/player.py
kinomusic/test.py
kinomusic/volumembed.py