Metadata-Version: 2.1
Name: ebesumusic
Version: 5.2.8
Summary: ebesumusic python discord
Home-page: https://github.com/Spidy20/PyMusic_Player
Author: Kushal Bhavsar
License: UNKNOWN
Keywords: music player python,music player tkinter,music player gui
Platform: UNKNOWN
Classifier: Programming Language :: Python :: 3
Classifier: License :: OSI Approved :: MIT License
Classifier: Operating System :: OS Independent
License-File: LICENSE
